wokelo_docs/__init__.py
wokelo_docs/docx/__init__.py
wokelo_docs/docx/api.py
wokelo_docs/docx/blkcntnr.py
wokelo_docs/docx/compat.py
wokelo_docs/docx/document.py
wokelo_docs/docx/exceptions.py
wokelo_docs/docx/package.py
wokelo_docs/docx/section.py
wokelo_docs/docx/settings.py
wokelo_docs/docx/shape.py
wokelo_docs/docx/shared.py
wokelo_docs/docx/table.py
wokelo_docs/docx/dml/__init__.py
wokelo_docs/docx/dml/color.py
wokelo_docs/docx/enum/__init__.py
wokelo_docs/docx/enum/base.py
wokelo_docs/docx/enum/dml.py
wokelo_docs/docx/enum/section.py
wokelo_docs/docx/enum/shape.py
wokelo_docs/docx/enum/style.py
wokelo_docs/docx/enum/table.py
wokelo_docs/docx/enum/text.py
wokelo_docs/docx/image/__init__.py
wokelo_docs/docx/image/bmp.py
wokelo_docs/docx/image/constants.py
wokelo_docs/docx/image/emf.py
wokelo_docs/docx/image/exceptions.py
wokelo_docs/docx/image/gif.py
wokelo_docs/docx/image/helpers.py
wokelo_docs/docx/image/image.py
wokelo_docs/docx/image/jpeg.py
wokelo_docs/docx/image/png.py
wokelo_docs/docx/image/tiff.py
wokelo_docs/docx/opc/__init__.py
wokelo_docs/docx/opc/compat.py
wokelo_docs/docx/opc/constants.py
wokelo_docs/docx/opc/coreprops.py
wokelo_docs/docx/opc/exceptions.py
wokelo_docs/docx/opc/oxml.py
wokelo_docs/docx/opc/package.py
wokelo_docs/docx/opc/packuri.py
wokelo_docs/docx/opc/part.py
wokelo_docs/docx/opc/phys_pkg.py
wokelo_docs/docx/opc/pkgreader.py
wokelo_docs/docx/opc/pkgwriter.py
wokelo_docs/docx/opc/rel.py
wokelo_docs/docx/opc/shared.py
wokelo_docs/docx/opc/spec.py
wokelo_docs/docx/opc/parts/__init__.py
wokelo_docs/docx/opc/parts/coreprops.py
wokelo_docs/docx/oxml/__init__.py
wokelo_docs/docx/oxml/comments.py
wokelo_docs/docx/oxml/coreprops.py
wokelo_docs/docx/oxml/document.py
wokelo_docs/docx/oxml/exceptions.py
wokelo_docs/docx/oxml/footnotes.py
wokelo_docs/docx/oxml/ns.py
wokelo_docs/docx/oxml/numbering.py
wokelo_docs/docx/oxml/section.py
wokelo_docs/docx/oxml/settings.py
wokelo_docs/docx/oxml/shape.py
wokelo_docs/docx/oxml/shared.py
wokelo_docs-0.1.0.dist-info/licenses/LICENSE
wokelo_docs-0.1.0.dist-info/METADATA
wokelo_docs-0.1.0.dist-info/WHEEL
wokelo_docs-0.1.0.dist-info/top_level.txt
wokelo_docs-0.1.0.dist-info/RECORD
