Metadata-Version: 2.4
Name: wokelo-docs
Version: 0.1.0
Summary: Combined package for creating, reading, and updating DOCX and PPTX files
Author: Wokelo
Author-email: support@wokelo.ai
Maintainer-email: Wokelo <support@wokelo.ai>
License: MIT, Apache-2.0
Project-URL: Homepage, https://github.com/Wokelo-AI/wokelo-docs
Project-URL: Repository, https://github.com/Wokelo-AI/wokelo-docs
Keywords: powerpoint,ppt,pptx,word,docx,openxml,office,wokelo
Classifier: Development Status :: 5 - Production/Stable
Classifier: Environment :: Console
Classifier: Intended Audience :: Developers
Classifier: License :: OSI Approved :: MIT License
Classifier: License :: OSI Approved :: Apache Software License
Classifier: Operating System :: OS Independent
Classifier: Programming Language :: Python
Classifier: Programming Language :: Python :: 3
Classifier: Programming Language :: Python :: 3.8
Classifier: Programming Language :: Python :: 3.9
Classifier: Programming Language :: Python :: 3.10
Classifier: Programming Language :: Python :: 3.11
Classifier: Programming Language :: Python :: 3.12
Classifier: Topic :: Office/Business :: Office Suites
Classifier: Topic :: Software Development :: Libraries
Requires-Python: >=3.8
License-File: LICENSE
Requires-Dist: Pillow>=3.3.2
Requires-Dist: XlsxWriter>=0.5.7
Requires-Dist: lxml>=3.1.0
Requires-Dist: typing_extensions>=4.9.0
Dynamic: license-file
